sd_python_wrapper-0.1.36.dist-info/DESCRIPTION.rst
sd_python_wrapper-0.1.36.dist-info/METADATA
sd_python_wrapper-0.1.36.dist-info/RECORD
sd_python_wrapper-0.1.36.dist-info/WHEEL
sd_python_wrapper-0.1.36.dist-info/metadata.json
sd_python_wrapper-0.1.36.dist-info/top_level.txt
serverdensity/__init__.py
serverdensity/response.py
serverdensity/wrapper/__init__.py
serverdensity/wrapper/alert.py
serverdensity/wrapper/apiclient.py
serverdensity/wrapper/crud.py
serverdensity/wrapper/dashboard.py
serverdensity/wrapper/device.py
serverdensity/wrapper/exceptions.py
serverdensity/wrapper/jsonobject.py
serverdensity/wrapper/metrics.py
serverdensity/wrapper/postback.py
serverdensity/wrapper/service.py
serverdensity/wrapper/service_status.py
serverdensity/wrapper/tag.py
serverdensity/wrapper/user.py
serverdensity/wrapper/widget.py
serverdensity/wrapper/schema/alerts.json
serverdensity/wrapper/schema/dashboards.json
serverdensity/wrapper/schema/devices.json
serverdensity/wrapper/schema/services.json
serverdensity/wrapper/schema/tags.json
serverdensity/wrapper/schema/testschema.json
serverdensity/wrapper/schema/users.json
serverdensity/wrapper/schema/widgets.json
tests/__init__.py
tests/basetest.py
tests/test_alert.py
tests/test_api.py
tests/test_dashboard.py
tests/test_device.py
tests/test_jsonobject.py
tests/test_postback.py
tests/test_response.py
tests/test_service.py
tests/test_service_status.py
tests/test_tag.py
tests/test_user.py
tests/test_widget.py
tests/json/alert.json
tests/json/dashboard.json
tests/json/device.json
tests/json/service.json
tests/json/tag.json
tests/json/user.json
tests/json/widget.json
