Metadata-Version: 2.0
Name: sd-python-wrapper
Version: 0.1.36
Summary: A python wrapper for the Server Density Api
Home-page: https://github.com/serverdensity/sd-python-wrapper
Author: Jonathan Sundqvist
Author-email: hello@serverdensity.com
License: MIT
Keywords: monitoring,serverdensity
Platform: UNKNOWN
Classifier: Development Status :: 2 - Pre-Alpha
Classifier: Intended Audience :: Developers
Classifier: Natural Language :: English
Classifier: Programming Language :: Python :: 2
Classifier: Programming Language :: Python :: 2.6
Classifier: Programming Language :: Python :: 2.7
Classifier: Programming Language :: Python :: 3
Classifier: Programming Language :: Python :: 3.3
Classifier: Programming Language :: Python :: 3.4
Classifier: Programming Language :: Python :: 3.5
Requires-Dist: isodate
Requires-Dist: jsonschema
Requires-Dist: requests
